pyodm/__init__.py
pyodm/api.py
pyodm/exceptions.py
pyodm/types.py
pyodm/utils.py
pyodm-1.5.12.dist-info/LICENSE
pyodm-1.5.12.dist-info/METADATA
pyodm-1.5.12.dist-info/WHEEL
pyodm-1.5.12.dist-info/top_level.txt
pyodm-1.5.12.dist-info/RECORD
