Metadata-Version: 2.1
Name: pyodm
Version: 1.5.12
Summary: Python SDK for OpenDroneMap
Home-page: https://github.com/OpenDroneMap/PyODM
Author: OpenDroneMap Contributors
Author-email: pt@uav4geo.com
Classifier: Programming Language :: Python :: 3
Classifier: License :: OSI Approved :: BSD License
Classifier: Operating System :: OS Independent
License-File: LICENSE
Requires-Dist: requests
Requires-Dist: requests_toolbelt
Requires-Dist: urllib3
